{
  "type": "code",
  "language": "text",
  "filename": "Project root",
  "description": "The complete project file structure. Every file listed here is explained in detail later in this section.",
  "code": "webdevguide/\n  .github/\n    workflows/\n      ci.yml                        # GitHub Actions CI/CD pipeline\n  docker-compose.yml                # Production containers\n  docker-compose.dev.yml            # Dev with volume mounts for hot reload\n\n  backend/\n    Dockerfile                      # Multi-stage Python build\n    requirements.txt                # Flask, Flask-Cors, gunicorn\n    entrypoint.py                   # Seeds DB then starts gunicorn\n    app/\n      __init__.py                   # App factory (create_app) + resolve_ref + seed-db CLI\n      config.py                     # Dev/Testing/Prod config classes\n      extensions.py                 # CORS initialization\n      api/\n        guide.py                    # Blueprint: /api/guide/* (sections, navigation)\n        exam.py                     # Blueprint: /api/exam/* (questions, categories)\n        glossary.py                 # Blueprint: /api/glossary/* (terms, search)\n      services/\n        guide_service.py            # Section queries (get_all, get_by_slug, navigation)\n        exam_service.py             # Random sampling, category filtering\n        glossary_service.py         # Term lookup, search, categories\n      utils/\n        db.py                       # JsonDatabase class + init_db + get_db\n    seeds/\n      data/\n        index.json                  # Root $ref map: slug -> section file\n        exam_questions.json         # All exam questions\n        glossary_terms.json         # All glossary terms\n        sections/\n          getting-started.json      # One file per guide section\n          fundamentals.json\n          building-this-guide.json  # This very file\n          ...                       # 30+ section files\n\n  frontend/\n    Dockerfile                      # Multi-stage Node.js build\n    package.json                    # Next.js 15, React 19, MUI 6, Redux Toolkit\n    next.config.ts                  # Next.js config with next-intl plugin\n    src/\n      app/\n        layout.tsx                  # Root layout (html, body, metadata)\n        [locale]/\n          layout.tsx                # Locale layout (i18n, Store, Theme, Header, Footer)\n          page.tsx                  # Home page\n          getting-started/page.tsx  # One page.tsx per guide section\n          building-this-guide/page.tsx\n          exam/page.tsx\n          glossary/page.tsx\n          ...\n      components/\n        content/\n          BlockRenderer.tsx         # Dispatcher: switches on block.type\n          SectionRenderer.tsx       # Maps blocks to BlockRenderer\n          GuidePageLayout.tsx       # Full page layout with title, chips, keypoints\n          TextBlockRenderer.tsx     # Renders text blocks with markdown\n          CodeBlockRenderer.tsx     # Syntax highlighting + copy button\n          AlertBlockRenderer.tsx    # Info/warning/success/error callouts\n          ListBlockRenderer.tsx     # Ordered and unordered lists\n          StepBlockRenderer.tsx     # Numbered tutorial steps\n          TabsBlockRenderer.tsx     # Tabbed content panels\n          AccordionBlockRenderer.tsx # Expandable sections\n          TableBlockRenderer.tsx    # Data tables\n          CardGridBlockRenderer.tsx # Grid of feature cards\n          KeyPointsList.tsx         # Summary points at bottom\n        layout/\n          Header.tsx                # Top navigation bar\n          Footer.tsx                # Site footer\n        common/\n          BookmarkButton.tsx        # Add/remove bookmark\n          LoadingSpinner.tsx        # Loading state\n      store/\n        store.ts                    # Redux store with persistence config\n        hooks.ts                    # Typed useAppDispatch, useAppSelector\n        StoreProvider.tsx           # PersistGate + Provider wrapper\n        slices/\n          themeSlice.ts             # Light/dark mode toggle\n          guideSlice.ts             # Section fetching + currentSection\n          examSlice.ts              # Exam state, scoring, history\n          glossarySlice.ts          # Glossary terms + filtering\n          bookmarkSlice.ts          # User bookmarks with notes\n          progressSlice.ts          # Reading progress tracking\n          generatorSlice.ts         # Code generator configuration\n      lib/\n        apiClient.ts                # Axios instance + guideApi, examApi, glossaryApi\n      theme/\n        theme.ts                    # getTheme(mode) factory\n        palette.ts                  # Light and dark color palettes\n        typography.ts               # Font configuration\n        components.ts               # MUI component overrides\n        ThemeRegistry.tsx           # CacheProvider + ThemeProvider + CssBaseline\n      i18n/\n        routing.ts                  # Locale definitions (en, localePrefix: as-needed)\n        request.ts                  # Server-side locale loading\n        navigation.ts               # Localized navigation helpers\n      hooks/\n        useHeader.ts                # Nav items + More menu groups\n      messages/\n        en.json                     # English translation strings\n      types/\n        content.ts                  # ContentBlock union type + GuideSectionContent\n        exam.ts                     # ExamQuestion type\n        guide.ts                    # GuideSection + GlossaryTerm types"
}
